textractoverlayer/__init__.py
textractoverlayer/_version.py
textractoverlayer/image_tools.py
textractoverlayer/t_overlay.py
amazon_textract_overlayer-0.0.12.dist-info/LICENSE
amazon_textract_overlayer-0.0.12.dist-info/METADATA
amazon_textract_overlayer-0.0.12.dist-info/WHEEL
amazon_textract_overlayer-0.0.12.dist-info/top_level.txt
amazon_textract_overlayer-0.0.12.dist-info/RECORD
