Metadata-Version: 2.1
Name: amazon-textract-overlayer
Version: 0.0.12
Summary: Amazon Textract Overlay tools
Home-page: https://github.com/aws-samples/amazon-textract-textractor/tree/master/overlayer
Author: Amazon Rekognition Textract Demoes
Author-email: rekognition-textract-demos@amazon.com
License: Apache License Version 2.0
Keywords: amazon-textract-textractor amazon textract textractor helper overlayer
Platform: UNKNOWN
Classifier: Development Status :: 4 - Beta
Classifier: Topic :: Utilities
Classifier: License :: OSI Approved :: Apache Software License
Classifier: Programming Language :: Python :: 3.6
Classifier: Programming Language :: Python :: 3.7
Classifier: Programming Language :: Python :: 3.8
Classifier: Programming Language :: Python :: 3.9
Classifier: Programming Language :: Python :: 3.10
Requires-Python: >=3.6
Requires-Dist: boto3
Requires-Dist: botocore
Requires-Dist: amazon-textract-caller (>=0.0.11)
Requires-Dist: Pillow
Requires-Dist: pypdf (<4.0,>=3.1)
